<?xml version="1.0" encoding="utf-8" ?>
<dwsync>
<file name="_magic_quotes_inputs.php" server="diecasthobbyshop.com/diecasthobbyshop.com/" local="129423441000000000" remote="129423441000000000" />
<file name="magic_quotes_gpc_off.php" server="diecasthobbyshop.com/diecasthobbyshop.com/" local="129423441000000000" remote="129423441000000000" />
<file name="magic_quotes_gpc_on.php" server="diecasthobbyshop.com/diecasthobbyshop.com/" local="129423441000000000" remote="129423441000000000" />
<file name="magic_quotes_sybase_off.php" server="diecasthobbyshop.com/diecasthobbyshop.com/" local="129423441000000000" remote="129423441000000000" />
<file name="magic_quotes_sybase_on.php" server="diecasthobbyshop.com/diecasthobbyshop.com/" local="129423441000000000" remote="129423441000000000" />
<file name="register_argc_argv_off.php" server="diecasthobbyshop.com/diecasthobbyshop.com/" local="129423441000000000" remote="129423441000000000" />
<file name="register_globals_off.php" server="diecasthobbyshop.com/diecasthobbyshop.com/" local="129423441000000000" remote="129423441000000000" />
<file name="register_globals_on.php" server="diecasthobbyshop.com/diecasthobbyshop.com/" local="129423441000000000" remote="129423441000000000" />
<file name="register_long_arrays_off.php" server="diecasthobbyshop.com/diecasthobbyshop.com/" local="129423441000000000" remote="129423441000000000" />
<file name="register_long_arrays_on.php" server="diecasthobbyshop.com/diecasthobbyshop.com/" local="129423441000000000" remote="129423441000000000" />
<file name="request_uri.php" server="diecasthobbyshop.com/diecasthobbyshop.com/" local="129423441000000000" remote="129423441000000000" />
</dwsync>